_meos_cffi.abi3.so
pymeos_cffi/errors.py
pymeos_cffi/__init__.py
pymeos_cffi/enums.py
pymeos_cffi/functions.py
pymeos_cffi/proj_data/proj.ini
pymeos_cffi/proj_data/triangulation.schema.json
pymeos_cffi/proj_data/ITRF2000
pymeos_cffi/proj_data/nad27
pymeos_cffi/proj_data/proj.db
pymeos_cffi/proj_data/CH
pymeos_cffi/proj_data/ITRF2014
pymeos_cffi/proj_data/deformation_model.schema.json
pymeos_cffi/proj_data/projjson.schema.json
pymeos_cffi/proj_data/world
pymeos_cffi/proj_data/other.extra
pymeos_cffi/proj_data/nad.lst
pymeos_cffi/proj_data/nad83
pymeos_cffi/proj_data/GL27
pymeos_cffi/proj_data/ITRF2008
pymeos_cffi.libs/libcom_err-2abe824b.so.2.1
pymeos_cffi.libs/libgssapi_krb5-497db0c6.so.2.2
pymeos_cffi.libs/libnssutil3-3492aa84.so
pymeos_cffi.libs/libgeos_c-f0a3a27a.so.1.14.3
pymeos_cffi.libs/libssl-cd1d6220.so.1.0.2k
pymeos_cffi.libs/libcurl-34c6b10f.so.4.3.0
pymeos_cffi.libs/libjpeg-43436dd5.so.62.1.0
pymeos_cffi.libs/libpcre-9513aab5.so.1.2.0
pymeos_cffi.libs/libldap-2-b8523ca2.4.so.2.10.7
pymeos_cffi.libs/libnss3-77677daf.so
pymeos_cffi.libs/libidn-97d26f25.so.11.6.11
pymeos_cffi.libs/liblber-2-7eefa761.4.so.2.10.7
pymeos_cffi.libs/libplc4-690d9cce.so
pymeos_cffi.libs/libssl3-b5783e6f.so
pymeos_cffi.libs/libkrb5support-d0bcff84.so.0.1
pymeos_cffi.libs/libmeos-d5e122da.so
pymeos_cffi.libs/libkeyutils-dfe70bd6.so.1.5
pymeos_cffi.libs/libgsl-cb3064f9.so.0.16.0
pymeos_cffi.libs/libcrypto-d3570994.so.1.0.2k
pymeos_cffi.libs/libcrypt-8f974802.so.1
pymeos_cffi.libs/libsatlas-7e2f78d2.so.3.10
pymeos_cffi.libs/libsqlite3-abbb757a.so.0.8.6
pymeos_cffi.libs/libtiff-b6eb22fb.so.5.2.0
pymeos_cffi.libs/libgslcblas-9055a056.so.0.0.0
pymeos_cffi.libs/libproj-6487d66e.so.22.1.1
pymeos_cffi.libs/libplds4-c4b42550.so
pymeos_cffi.libs/libgfortran-91cc3cb1.so.3.0.0
pymeos_cffi.libs/libsmime3-1ce58481.so
pymeos_cffi.libs/libselinux-0922c95c.so.1
pymeos_cffi.libs/libgeos-3-ee4b22ec.9.2.so
pymeos_cffi.libs/libjson-c-a9e3991b.so.5.3.0
pymeos_cffi-1.2.0.dist-info/top_level.txt
pymeos_cffi-1.2.0.dist-info/RECORD
pymeos_cffi-1.2.0.dist-info/LICENSE
pymeos_cffi-1.2.0.dist-info/METADATA
pymeos_cffi-1.2.0.dist-info/WHEEL
