Metadata-Version: 2.1
Name: pymeos_cffi
Version: 1.2.0
Summary: PyMEOS wrapper for the MEOS C Library.
Author-email: Victor Divi <vdiviloper@gmail.com>
License: PostgreSQL License
Project-URL: Homepage, https://github.com/MobilityDB/PyMEOS
Project-URL: Bug Tracker, https://github.com/MobilityDB/PyMEOS/issues
Classifier: License :: OSI Approved :: PostgreSQL License
Classifier: Development Status :: 4 - Beta
Classifier: Intended Audience :: Developers
Classifier: Intended Audience :: Science/Research
Classifier: Programming Language :: C
Classifier: Programming Language :: Python
Classifier: Programming Language :: Python :: 3
Classifier: Programming Language :: Python :: 3.8
Classifier: Programming Language :: Python :: 3.9
Classifier: Programming Language :: Python :: 3.10
Classifier: Programming Language :: Python :: 3.11
Classifier: Programming Language :: Python :: 3 :: Only
Classifier: Programming Language :: Python :: Implementation :: CPython
Classifier: Operating System :: POSIX
Classifier: Operating System :: Unix
Requires-Python: >=3.8
License-File: LICENSE
Requires-Dist: cffi
Requires-Dist: python-dateutil
Requires-Dist: shapely
